[
    {
        "writer_id": 10000,
        "writer_name": "حسین فرخی",
        "description": "سرعت اینترنت در این محل خوب نیست.",
        "building_id": 4,
        "created_at": "2024-08-26 15:12"
    },
    {
        "writer_id": 10001,
        "writer_name": "حسین مرادی",
        "description": "ساخت ملک نسبتاً جدید بود.",
        "building_id": 4,
        "created_at": "2024-08-28 16:47"
    },
    {
        "writer_id": 10002,
        "writer_name": "مینا مرادی",
        "description": "محله ملک جدید و مدرن است.",
        "building_id": 4,
        "created_at": "2024-08-19 05:35"
    },
    {
        "writer_id": 10003,
        "writer_name": "زهرا سلیمانی",
        "description": "پارکینگ شخصی ندارد و باید در خیابان پارک کرد.",
        "building_id": 4,
        "created_at": "2024-08-16 13:24"
    },
    {
        "writer_id": 10004,
        "writer_name": "نگار محمودی",
        "description": "خیلی بزرگ و دلباز بود.",
        "building_id": 4,
        "created_at": "2024-08-20 07:22"
    },
    {
        "writer_id": 10005,
        "writer_name": "نگار رضایی",
        "description": "برای خانواده‌ها خیلی مناسب نیست.",
        "building_id": 4,
        "created_at": "2024-08-21 08:28"
    },
    {
        "writer_id": 10006,
        "writer_name": "رضا سلیمانی",
        "description": "ملک دور از امکانات شهری بود.",
        "building_id": 4,
        "created_at": "2024-09-11 21:00"
    },
    {
        "writer_id": 10007,
        "writer_name": "مینا کریمی",
        "description": "خیلی تمیز و مرتب بود.",
        "building_id": 4,
        "created_at": "2024-08-16 01:42"
    },
    {
        "writer_id": 10008,
        "writer_name": "رضا کاظمی",
        "description": "قیمت ملک نسبت به شرایط آن مناسب است.",
        "building_id": 4,
        "created_at": "2024-08-17 01:28"
    },
    {
        "writer_id": 10009,
        "writer_name": "عرفان مرادی",
        "description": "سرعت اینترنت در این محل خوب نیست.",
        "building_id": 4,
        "created_at": "2024-08-23 20:12"
    },
    {
        "writer_id": 10010,
        "writer_name": "حسین کریمی",
        "description": "آشپزخانه کوچک است، اما قابل قبول.",
        "building_id": 4,
        "created_at": "2024-08-22 09:11"
    },
    {
        "writer_id": 10011,
        "writer_name": "محمد محمودی",
        "description": "از تهویه ملک رضایت دارم.",
        "building_id": 4,
        "created_at": "2024-08-30 16:16"
    },
    {
        "writer_id": 10012,
        "writer_name": "فاطمه موسوی",
        "description": "سرویس بهداشتی‌ها کوچک بودند.",
        "building_id": 4,
        "created_at": "2024-08-16 22:53"
    },
    {
        "writer_id": 10013,
        "writer_name": "فاطمه نعمتی",
        "description": "نزدیکی به پارک و فضای سبز یک مزیت بزرگ است.",
        "building_id": 4,
        "created_at": "2024-09-04 08:52"
    },
    {
        "writer_id": 10014,
        "writer_name": "زهرا سلیمانی",
        "description": "از تهویه ملک رضایت دارم.",
        "building_id": 4,
        "created_at": "2024-09-09 06:08"
    },
    {
        "writer_id": 10015,
        "writer_name": "علی محمودی",
        "description": "ساختار ملک خیلی قدیمی است.",
        "building_id": 4,
        "created_at": "2024-09-13 08:24"
    },
    {
        "writer_id": 10016,
        "writer_name": "عرفان کاظمی",
        "description": "فضای حیاط بزرگ و دلباز است.",
        "building_id": 4,
        "created_at": "2024-08-25 06:15"
    },
    {
        "writer_id": 10017,
        "writer_name": "علی سلیمانی",
        "description": "فضای حیاط بزرگ و دلباز است.",
        "building_id": 4,
        "created_at": "2024-08-28 10:18"
    },
    {
        "writer_id": 10018,
        "writer_name": "محمد سلیمانی",
        "description": "این ملک نیاز به بازسازی داشت.",
        "building_id": 4,
        "created_at": "2024-09-01 04:24"
    },
    {
        "writer_id": 10019,
        "writer_name": "علی رضایی",
        "description": "فضای داخلی طراحی مدرنی داشت.",
        "building_id": 4,
        "created_at": "2024-09-01 04:59"
    },
    {
        "writer_id": 10020,
        "writer_name": "محمد فرخی",
        "description": "تمیز و مرتب بود، ولی پارکینگ کوچک داشت.",
        "building_id": 4,
        "created_at": "2024-08-31 21:19"
    },
    {
        "writer_id": 10021,
        "writer_name": "مینا نعمتی",
        "description": "سیستم گرمایشی خوب کار نمی‌کرد.",
        "building_id": 4,
        "created_at": "2024-08-20 00:19"
    },
    {
        "writer_id": 10022,
        "writer_name": "عرفان رضایی",
        "description": "پارکینگ شخصی ندارد و باید در خیابان پارک کرد.",
        "building_id": 4,
        "created_at": "2024-08-15 16:58"
    },
    {
        "writer_id": 10023,
        "writer_name": "عرفان کاظمی",
        "description": "آب و هوای محله بسیار خوب است.",
        "building_id": 4,
        "created_at": "2024-08-16 11:20"
    },
    {
        "writer_id": 10024,
        "writer_name": "عرفان احمدی",
        "description": "از خرید خود راضی هستم.",
        "building_id": 4,
        "created_at": "2024-09-07 14:51"
    },
    {
        "writer_id": 10025,
        "writer_name": "زهرا احمدی",
        "description": "فضای نشیمن بزرگ و جادار بود.",
        "building_id": 4,
        "created_at": "2024-08-18 09:50"
    },
    {
        "writer_id": 10026,
        "writer_name": "عرفان مرادی",
        "description": "تمیز و مرتب بود، ولی پارکینگ کوچک داشت.",
        "building_id": 4,
        "created_at": "2024-08-22 16:48"
    },
    {
        "writer_id": 10027,
        "writer_name": "علی موسوی",
        "description": "ملک از عکس‌ها بهتر بود.",
        "building_id": 4,
        "created_at": "2024-09-13 08:03"
    },
    {
        "writer_id": 10028,
        "writer_name": "علی مرادی",
        "description": "ملک به مرکز خرید نزدیک است.",
        "building_id": 4,
        "created_at": "2024-09-13 08:20"
    },
    {
        "writer_id": 10029,
        "writer_name": "حسین رضایی",
        "description": "سرویس بهداشتی‌ها کوچک بودند.",
        "building_id": 4,
        "created_at": "2024-09-09 08:37"
    },
    {
        "writer_id": 10030,
        "writer_name": "محمد موسوی",
        "description": "فضای حیاط بزرگ و دلباز است.",
        "building_id": 4,
        "created_at": "2024-08-22 22:59"
    },
    {
        "writer_id": 10031,
        "writer_name": "زهرا نعمتی",
        "description": "ملک دور از امکانات شهری بود.",
        "building_id": 4,
        "created_at": "2024-08-31 14:20"
    },
    {
        "writer_id": 10032,
        "writer_name": "مینا کریمی",
        "description": "محیط بسیار ساکت و آرام است.",
        "building_id": 4,
        "created_at": "2024-09-06 04:38"
    },
    {
        "writer_id": 10033,
        "writer_name": "زهرا مرادی",
        "description": "به نسبت قیمت، امکانات مناسبی دارد.",
        "building_id": 4,
        "created_at": "2024-09-06 05:45"
    },
    {
        "writer_id": 10034,
        "writer_name": "عرفان موسوی",
        "description": "سروصدای زیاد از خیابان وجود داشت.",
        "building_id": 4,
        "created_at": "2024-08-28 19:32"
    },
    {
        "writer_id": 10035,
        "writer_name": "مینا موسوی",
        "description": "فضای داخلی طراحی مدرنی داشت.",
        "building_id": 4,
        "created_at": "2024-08-16 17:14"
    },
    {
        "writer_id": 10036,
        "writer_name": "علی نعمتی",
        "description": "ملک قدیمی است، اما موقعیت خوبی دارد.",
        "building_id": 4,
        "created_at": "2024-08-24 06:10"
    },
    {
        "writer_id": 10037,
        "writer_name": "نگار کریمی",
        "description": "سیستم ایمنی خوبی دارد.",
        "building_id": 4,
        "created_at": "2024-08-23 15:10"
    },
    {
        "writer_id": 10038,
        "writer_name": "محمد مرادی",
        "description": "فضای نشیمن بزرگ و جادار بود.",
        "building_id": 4,
        "created_at": "2024-08-22 17:19"
    },
    {
        "writer_id": 10039,
        "writer_name": "احمد کریمی",
        "description": "ملک از عکس‌ها بهتر بود.",
        "building_id": 4,
        "created_at": "2024-09-07 21:33"
    },
    {
        "writer_id": 10040,
        "writer_name": "علی کریمی",
        "description": "نورگیر بسیار عالی است.",
        "building_id": 4,
        "created_at": "2024-09-11 06:52"
    },
    {
        "writer_id": 10041,
        "writer_name": "زهرا احمدی",
        "description": "محل پارکینگ کوچک است و مشکل‌ساز است.",
        "building_id": 4,
        "created_at": "2024-08-15 16:14"
    },
    {
        "writer_id": 10042,
        "writer_name": "فاطمه مرادی",
        "description": "سیستم گرمایشی خوب کار نمی‌کرد.",
        "building_id": 4,
        "created_at": "2024-08-27 16:00"
    },
    {
        "writer_id": 10043,
        "writer_name": "فاطمه سلیمانی",
        "description": "سرعت اینترنت در این محل خوب نیست.",
        "building_id": 4,
        "created_at": "2024-08-30 02:47"
    },
    {
        "writer_id": 10044,
        "writer_name": "حسین مرادی",
        "description": "دسترسی به مراکز خرید خیلی خوب بود.",
        "building_id": 4,
        "created_at": "2024-08-17 19:04"
    },
    {
        "writer_id": 10045,
        "writer_name": "مینا سلیمانی",
        "description": "آشپزخانه کوچک است، اما قابل قبول.",
        "building_id": 4,
        "created_at": "2024-09-04 16:30"
    },
    {
        "writer_id": 10046,
        "writer_name": "حسین کاظمی",
        "description": "آب و هوای محله بسیار خوب است.",
        "building_id": 4,
        "created_at": "2024-09-05 04:30"
    },
    {
        "writer_id": 10047,
        "writer_name": "احمد مرادی",
        "description": "آب و هوای محله بسیار خوب است.",
        "building_id": 4,
        "created_at": "2024-08-20 20:59"
    },
    {
        "writer_id": 10048,
        "writer_name": "علی فرخی",
        "description": "پارکینگ کافی نبود و باید روی خیابان پارک کنیم.",
        "building_id": 4,
        "created_at": "2024-08-21 10:42"
    },
    {
        "writer_id": 10049,
        "writer_name": "حسین کاظمی",
        "description": "همسایه‌ها خیلی مهربان و کمک‌کننده بودند.",
        "building_id": 4,
        "created_at": "2024-09-12 02:26"
    },
    {
        "writer_id": 10050,
        "writer_name": "عرفان احمدی",
        "description": "سیستم گرمایشی خوب کار نمی‌کرد.",
        "building_id": 4,
        "created_at": "2024-08-15 10:57"
    },
    {
        "writer_id": 10051,
        "writer_name": "احمد احمدی",
        "description": "خدمات محلی و دسترسی به سوپرمارکت عالی است.",
        "building_id": 4,
        "created_at": "2024-09-11 17:41"
    },
    {
        "writer_id": 10052,
        "writer_name": "محمد سلیمانی",
        "description": "محله ملک جدید و مدرن است.",
        "building_id": 4,
        "created_at": "2024-08-28 07:56"
    },
    {
        "writer_id": 10053,
        "writer_name": "علی موسوی",
        "description": "سروصدای زیاد از خیابان وجود داشت.",
        "building_id": 4,
        "created_at": "2024-08-21 06:18"
    },
    {
        "writer_id": 10054,
        "writer_name": "علی کاظمی",
        "description": "قیمت ملک نسبت به شرایط آن مناسب است.",
        "building_id": 4,
        "created_at": "2024-08-25 02:50"
    },
    {
        "writer_id": 10055,
        "writer_name": "محمد موسوی",
        "description": "ساختار ملک خیلی قدیمی است.",
        "building_id": 4,
        "created_at": "2024-08-14 19:20"
    },
    {
        "writer_id": 10056,
        "writer_name": "نگار نعمتی",
        "description": "این ملک نیاز به بازسازی داشت.",
        "building_id": 4,
        "created_at": "2024-08-14 05:33"
    },
    {
        "writer_id": 10057,
        "writer_name": "فاطمه رضایی",
        "description": "سیستم گرمایشی خوب کار نمی‌کرد.",
        "building_id": 4,
        "created_at": "2024-09-01 21:44"
    },
    {
        "writer_id": 10058,
        "writer_name": "حسین فرخی",
        "description": "نورگیر بسیار عالی است.",
        "building_id": 4,
        "created_at": "2024-09-03 15:09"
    },
    {
        "writer_id": 10059,
        "writer_name": "رضا احمدی",
        "description": "محل پارکینگ کوچک است و مشکل‌ساز است.",
        "building_id": 4,
        "created_at": "2024-08-27 08:13"
    },
    {
        "writer_id": 10060,
        "writer_name": "نگار کاظمی",
        "description": "سیستم ایمنی خوبی دارد.",
        "building_id": 4,
        "created_at": "2024-09-04 06:02"
    },
    {
        "writer_id": 10061,
        "writer_name": "فاطمه فرخی",
        "description": "ملک از عکس‌ها بهتر بود.",
        "building_id": 4,
        "created_at": "2024-08-29 00:49"
    },
    {
        "writer_id": 10062,
        "writer_name": "حسین نعمتی",
        "description": "نورگیر بسیار عالی است.",
        "building_id": 4,
        "created_at": "2024-08-29 08:06"
    },
    {
        "writer_id": 10063,
        "writer_name": "محمد سلیمانی",
        "description": "آسانسور خراب بود و نیاز به تعمیر داشت.",
        "building_id": 4,
        "created_at": "2024-08-19 02:49"
    },
    {
        "writer_id": 10064,
        "writer_name": "حسین نعمتی",
        "description": "محیط بسیار ساکت و آرام است.",
        "building_id": 4,
        "created_at": "2024-08-15 03:47"
    },
    {
        "writer_id": 10065,
        "writer_name": "رضا فرخی",
        "description": "تمیز و مرتب بود، ولی پارکینگ کوچک داشت.",
        "building_id": 4,
        "created_at": "2024-09-08 23:54"
    },
    {
        "writer_id": 10066,
        "writer_name": "مینا احمدی",
        "description": "ملک به مرکز خرید نزدیک است.",
        "building_id": 4,
        "created_at": "2024-08-20 18:02"
    },
    {
        "writer_id": 10067,
        "writer_name": "احمد کاظمی",
        "description": "نورگیر بسیار عالی است.",
        "building_id": 4,
        "created_at": "2024-09-07 13:01"
    },
    {
        "writer_id": 10068,
        "writer_name": "مینا سلیمانی",
        "description": "همسایه‌ها خیلی مهربان و کمک‌کننده بودند.",
        "building_id": 4,
        "created_at": "2024-08-21 09:47"
    },
    {
        "writer_id": 10069,
        "writer_name": "حسین موسوی",
        "description": "سروصدای زیاد از خیابان وجود داشت.",
        "building_id": 4,
        "created_at": "2024-08-23 09:15"
    },
    {
        "writer_id": 10070,
        "writer_name": "علی سلیمانی",
        "description": "با وجود اینکه ملک قدیمی است، باز هم ارزش خرید دارد.",
        "building_id": 4,
        "created_at": "2024-09-11 08:19"
    },
    {
        "writer_id": 10071,
        "writer_name": "مینا محمودی",
        "description": "بسیار نزدیک به مدارس و دانشگاه‌ها است.",
        "building_id": 4,
        "created_at": "2024-09-08 10:29"
    },
    {
        "writer_id": 10072,
        "writer_name": "علی مرادی",
        "description": "تمیز و مرتب بود، ولی پارکینگ کوچک داشت.",
        "building_id": 4,
        "created_at": "2024-09-05 02:43"
    },
    {
        "writer_id": 10073,
        "writer_name": "رضا سلیمانی",
        "description": "آب و هوای محله بسیار خوب است.",
        "building_id": 4,
        "created_at": "2024-09-12 20:03"
    },
    {
        "writer_id": 10074,
        "writer_name": "رضا سلیمانی",
        "description": "قیمت ملک نسبت به شرایط آن مناسب است.",
        "building_id": 4,
        "created_at": "2024-08-31 08:32"
    },
    {
        "writer_id": 10075,
        "writer_name": "مینا سلیمانی",
        "description": "آشپزخانه کوچک است، اما قابل قبول.",
        "building_id": 4,
        "created_at": "2024-08-26 02:02"
    },
    {
        "writer_id": 10076,
        "writer_name": "نگار فرخی",
        "description": "هزینه‌های نگهداری ملک کمی بالا است.",
        "building_id": 4,
        "created_at": "2024-09-01 15:58"
    },
    {
        "writer_id": 10077,
        "writer_name": "مینا کریمی",
        "description": "سرویس بهداشتی‌ها کوچک بودند.",
        "building_id": 4,
        "created_at": "2024-08-15 01:12"
    },
    {
        "writer_id": 10078,
        "writer_name": "نگار احمدی",
        "description": "آب و هوای محله بسیار خوب است.",
        "building_id": 4,
        "created_at": "2024-08-15 21:48"
    },
    {
        "writer_id": 10079,
        "writer_name": "احمد محمودی",
        "description": "سیستم گرمایشی خوب کار نمی‌کرد.",
        "building_id": 4,
        "created_at": "2024-08-29 07:02"
    },
    {
        "writer_id": 10080,
        "writer_name": "حسین رضایی",
        "description": "ساخت ملک نسبتاً جدید بود.",
        "building_id": 4,
        "created_at": "2024-08-24 00:16"
    },
    {
        "writer_id": 10081,
        "writer_name": "زهرا رضایی",
        "description": "محیط بسیار ساکت و آرام است.",
        "building_id": 4,
        "created_at": "2024-08-30 10:03"
    },
    {
        "writer_id": 10082,
        "writer_name": "حسین سلیمانی",
        "description": "ملک قدیمی است، اما موقعیت خوبی دارد.",
        "building_id": 4,
        "created_at": "2024-09-13 14:10"
    },
    {
        "writer_id": 10083,
        "writer_name": "رضا نعمتی",
        "description": "به نسبت قیمت، امکانات مناسبی دارد.",
        "building_id": 4,
        "created_at": "2024-09-02 13:09"
    },
    {
        "writer_id": 10084,
        "writer_name": "حسین رضایی",
        "description": "این ملک نیاز به بازسازی داشت.",
        "building_id": 4,
        "created_at": "2024-08-20 11:08"
    },
    {
        "writer_id": 10085,
        "writer_name": "نگار رضایی",
        "description": "ملک بسیار تمیز و مرتب تحویل داده شد.",
        "building_id": 4,
        "created_at": "2024-08-27 17:45"
    },
    {
        "writer_id": 10086,
        "writer_name": "محمد سلیمانی",
        "description": "این ملک نیاز به بازسازی داشت.",
        "building_id": 4,
        "created_at": "2024-08-26 23:29"
    },
    {
        "writer_id": 10087,
        "writer_name": "حسین موسوی",
        "description": "سیستم ایمنی خوبی دارد.",
        "building_id": 4,
        "created_at": "2024-08-25 17:54"
    },
    {
        "writer_id": 10088,
        "writer_name": "فاطمه مرادی",
        "description": "سرویس بهداشتی‌ها کوچک بودند.",
        "building_id": 4,
        "created_at": "2024-08-16 14:17"
    },
    {
        "writer_id": 10089,
        "writer_name": "علی سلیمانی",
        "description": "از تهویه ملک رضایت دارم.",
        "building_id": 4,
        "created_at": "2024-09-08 05:17"
    },
    {
        "writer_id": 10090,
        "writer_name": "عرفان احمدی",
        "description": "ساختار ملک خیلی قدیمی است.",
        "building_id": 4,
        "created_at": "2024-08-20 02:58"
    },
    {
        "writer_id": 10091,
        "writer_name": "فاطمه کریمی",
        "description": "قیمت ملک نسبت به شرایط آن مناسب است.",
        "building_id": 4,
        "created_at": "2024-08-28 08:54"
    },
    {
        "writer_id": 10092,
        "writer_name": "عرفان رضایی",
        "description": "ملک در موقعیت خوبی قرار دارد.",
        "building_id": 4,
        "created_at": "2024-08-16 05:33"
    },
    {
        "writer_id": 10093,
        "writer_name": "حسین مرادی",
        "description": "با وجود اینکه ملک قدیمی است، باز هم ارزش خرید دارد.",
        "building_id": 4,
        "created_at": "2024-09-10 02:03"
    },
    {
        "writer_id": 10094,
        "writer_name": "زهرا فرخی",
        "description": "محیط بسیار ساکت و آرام است.",
        "building_id": 4,
        "created_at": "2024-09-07 03:53"
    },
    {
        "writer_id": 10095,
        "writer_name": "رضا مرادی",
        "description": "پارکینگ شخصی ندارد و باید در خیابان پارک کرد.",
        "building_id": 4,
        "created_at": "2024-08-17 07:04"
    },
    {
        "writer_id": 10096,
        "writer_name": "رضا سلیمانی",
        "description": "از خرید خود راضی هستم.",
        "building_id": 4,
        "created_at": "2024-09-07 03:12"
    },
    {
        "writer_id": 10097,
        "writer_name": "نگار کریمی",
        "description": "فضای اتاق‌ها نسبتاً کوچک است.",
        "building_id": 4,
        "created_at": "2024-09-01 08:27"
    },
    {
        "writer_id": 10098,
        "writer_name": "فاطمه نعمتی",
        "description": "محیط بسیار ساکت و آرام است.",
        "building_id": 4,
        "created_at": "2024-08-25 02:12"
    },
    {
        "writer_id": 10099,
        "writer_name": "عرفان فرخی",
        "description": "سرویس بهداشتی‌ها کوچک بودند.",
        "building_id": 4,
        "created_at": "2024-08-28 20:10"
    },
    {
        "writer_id": 10100,
        "writer_name": "محمد احمدی",
        "description": "سیستم ایمنی خوبی دارد.",
        "building_id": 4,
        "created_at": "2024-09-02 04:14"
    },
    {
        "writer_id": 10101,
        "writer_name": "فاطمه احمدی",
        "description": "فضای نشیمن بزرگ و جادار بود.",
        "building_id": 4,
        "created_at": "2024-08-16 13:29"
    },
    {
        "writer_id": 10102,
        "writer_name": "علی کریمی",
        "description": "خدمات محلی و دسترسی به سوپرمارکت عالی است.",
        "building_id": 4,
        "created_at": "2024-09-09 04:41"
    },
    {
        "writer_id": 10103,
        "writer_name": "فاطمه نعمتی",
        "description": "آشپزخانه کوچک است، اما قابل قبول.",
        "building_id": 4,
        "created_at": "2024-08-15 17:05"
    },
    {
        "writer_id": 10104,
        "writer_name": "مینا فرخی",
        "description": "خیلی تمیز و مرتب بود.",
        "building_id": 4,
        "created_at": "2024-09-10 05:51"
    },
    {
        "writer_id": 10105,
        "writer_name": "احمد رضایی",
        "description": "دسترسی به مراکز خرید خیلی خوب بود.",
        "building_id": 4,
        "created_at": "2024-08-14 03:45"
    },
    {
        "writer_id": 10106,
        "writer_name": "محمد کریمی",
        "description": "ملک به مرکز خرید نزدیک است.",
        "building_id": 4,
        "created_at": "2024-09-09 22:10"
    },
    {
        "writer_id": 10107,
        "writer_name": "حسین کریمی",
        "description": "ملک دور از امکانات شهری بود.",
        "building_id": 4,
        "created_at": "2024-08-16 20:10"
    },
    {
        "writer_id": 10108,
        "writer_name": "محمد محمودی",
        "description": "ملک به مرکز خرید نزدیک است.",
        "building_id": 4,
        "created_at": "2024-09-03 07:31"
    },
    {
        "writer_id": 10109,
        "writer_name": "فاطمه محمودی",
        "description": "نزدیکی به پارک و فضای سبز یک مزیت بزرگ است.",
        "building_id": 4,
        "created_at": "2024-08-18 10:26"
    },
    {
        "writer_id": 10110,
        "writer_name": "حسین رضایی",
        "description": "سرویس بهداشتی‌ها کوچک بودند.",
        "building_id": 4,
        "created_at": "2024-08-20 20:19"
    },
    {
        "writer_id": 10111,
        "writer_name": "فاطمه کاظمی",
        "description": "به نسبت قیمت، امکانات مناسبی دارد.",
        "building_id": 4,
        "created_at": "2024-08-26 16:25"
    },
    {
        "writer_id": 10112,
        "writer_name": "علی سلیمانی",
        "description": "نزدیکی به پارک و فضای سبز یک مزیت بزرگ است.",
        "building_id": 4,
        "created_at": "2024-08-24 04:03"
    },
    {
        "writer_id": 10113,
        "writer_name": "نگار مرادی",
        "description": "بسیار نزدیک به مدارس و دانشگاه‌ها است.",
        "building_id": 4,
        "created_at": "2024-08-29 11:56"
    },
    {
        "writer_id": 10114,
        "writer_name": "حسین سلیمانی",
        "description": "فضای نشیمن بزرگ و جادار بود.",
        "building_id": 4,
        "created_at": "2024-08-21 09:31"
    },
    {
        "writer_id": 10115,
        "writer_name": "احمد نعمتی",
        "description": "سر و صدای زیاد از خیابان وجود داشت.",
        "building_id": 4,
        "created_at": "2024-09-01 11:25"
    },
    {
        "writer_id": 10116,
        "writer_name": "رضا سلیمانی",
        "description": "سرعت اینترنت در این محل خوب نیست.",
        "building_id": 4,
        "created_at": "2024-09-13 14:30"
    },
    {
        "writer_id": 10117,
        "writer_name": "عرفان احمدی",
        "description": "آب و هوای محله بسیار خوب است.",
        "building_id": 4,
        "created_at": "2024-09-02 21:00"
    },
    {
        "writer_id": 10118,
        "writer_name": "زهرا محمودی",
        "description": "آب و هوای محله بسیار خوب است.",
        "building_id": 4,
        "created_at": "2024-08-28 20:03"
    },
    {
        "writer_id": 10119,
        "writer_name": "محمد کاظمی",
        "description": "خیلی بزرگ و دلباز بود.",
        "building_id": 4,
        "created_at": "2024-08-23 10:07"
    },
    {
        "writer_id": 10120,
        "writer_name": "مینا احمدی",
        "description": "ساختار ملک خیلی قدیمی است.",
        "building_id": 4,
        "created_at": "2024-09-06 06:38"
    },
    {
        "writer_id": 10121,
        "writer_name": "عرفان احمدی",
        "description": "با وجود اینکه ملک قدیمی است، باز هم ارزش خرید دارد.",
        "building_id": 4,
        "created_at": "2024-08-30 16:14"
    },
    {
        "writer_id": 10122,
        "writer_name": "حسین محمودی",
        "description": "بسیار نزدیک به مدارس و دانشگاه‌ها است.",
        "building_id": 4,
        "created_at": "2024-09-10 00:12"
    },
    {
        "writer_id": 10123,
        "writer_name": "فاطمه نعمتی",
        "description": "خدمات محلی و دسترسی به سوپرمارکت عالی است.",
        "building_id": 4,
        "created_at": "2024-08-19 01:34"
    },
    {
        "writer_id": 10124,
        "writer_name": "علی نعمتی",
        "description": "ساخت و ساز اطراف ملک زیاد بود.",
        "building_id": 4,
        "created_at": "2024-09-13 11:18"
    },
    {
        "writer_id": 10125,
        "writer_name": "محمد نعمتی",
        "description": "سیستم گرمایشی خوب کار نمی‌کرد.",
        "building_id": 4,
        "created_at": "2024-08-29 13:09"
    },
    {
        "writer_id": 10126,
        "writer_name": "رضا احمدی",
        "description": "با وجود اینکه ملک قدیمی است، باز هم ارزش خرید دارد.",
        "building_id": 4,
        "created_at": "2024-09-02 07:41"
    },
    {
        "writer_id": 10127,
        "writer_name": "احمد موسوی",
        "description": "ملک به مرکز خرید نزدیک است.",
        "building_id": 4,
        "created_at": "2024-09-09 16:17"
    },
    {
        "writer_id": 10128,
        "writer_name": "حسین رضایی",
        "description": "خیلی بزرگ و دلباز بود.",
        "building_id": 4,
        "created_at": "2024-09-01 09:31"
    },
    {
        "writer_id": 10129,
        "writer_name": "عرفان احمدی",
        "description": "برای خانواده‌ها خیلی مناسب نیست.",
        "building_id": 4,
        "created_at": "2024-08-23 21:56"
    },
    {
        "writer_id": 10130,
        "writer_name": "علی کریمی",
        "description": "فضای داخلی طراحی مدرنی داشت.",
        "building_id": 4,
        "created_at": "2024-09-06 22:37"
    },
    {
        "writer_id": 10131,
        "writer_name": "علی موسوی",
        "description": "ملک در نزدیکی ایستگاه مترو قرار دارد.",
        "building_id": 4,
        "created_at": "2024-09-11 11:59"
    },
    {
        "writer_id": 10132,
        "writer_name": "مینا کاظمی",
        "description": "سروصدای زیاد از خیابان وجود داشت.",
        "building_id": 4,
        "created_at": "2024-09-05 00:11"
    },
    {
        "writer_id": 10133,
        "writer_name": "زهرا محمودی",
        "description": "با وجود اینکه ملک قدیمی است، باز هم ارزش خرید دارد.",
        "building_id": 4,
        "created_at": "2024-08-26 00:30"
    },
    {
        "writer_id": 10134,
        "writer_name": "فاطمه موسوی",
        "description": "فضای نشیمن بزرگ و جادار بود.",
        "building_id": 4,
        "created_at": "2024-08-14 02:50"
    },
    {
        "writer_id": 10135,
        "writer_name": "مینا مرادی",
        "description": "برای خانواده‌ها خیلی مناسب نیست.",
        "building_id": 4,
        "created_at": "2024-09-01 04:03"
    },
    {
        "writer_id": 10136,
        "writer_name": "فاطمه کریمی",
        "description": "خیلی تمیز و مرتب بود.",
        "building_id": 4,
        "created_at": "2024-09-05 17:41"
    },
    {
        "writer_id": 10137,
        "writer_name": "علی نعمتی",
        "description": "به نظر می‌رسد مالک در نگهداری ملک کوتاهی کرده.",
        "building_id": 4,
        "created_at": "2024-08-19 06:07"
    },
    {
        "writer_id": 10138,
        "writer_name": "رضا نعمتی",
        "description": "ملک به مرکز خرید نزدیک است.",
        "building_id": 4,
        "created_at": "2024-09-12 12:10"
    },
    {
        "writer_id": 10139,
        "writer_name": "فاطمه احمدی",
        "description": "ملک به مرکز خرید نزدیک است.",
        "building_id": 4,
        "created_at": "2024-09-13 14:54"
    },
    {
        "writer_id": 10140,
        "writer_name": "مینا نعمتی",
        "description": "امکانات رفاهی اطراف ملک خیلی خوب است.",
        "building_id": 4,
        "created_at": "2024-09-09 20:21"
    },
    {
        "writer_id": 10141,
        "writer_name": "محمد سلیمانی",
        "description": "سر و صدای زیاد از خیابان وجود داشت.",
        "building_id": 4,
        "created_at": "2024-09-06 10:45"
    },
    {
        "writer_id": 10142,
        "writer_name": "حسین محمودی",
        "description": "نزدیکی به پارک و فضای سبز یک مزیت بزرگ است.",
        "building_id": 4,
        "created_at": "2024-09-07 23:30"
    },
    {
        "writer_id": 10143,
        "writer_name": "حسین کاظمی",
        "description": "بسیار نزدیک به مدارس و دانشگاه‌ها است.",
        "building_id": 4,
        "created_at": "2024-08-21 15:35"
    },
    {
        "writer_id": 10144,
        "writer_name": "نگار فرخی",
        "description": "پارکینگ کافی نبود و باید روی خیابان پارک کنیم.",
        "building_id": 4,
        "created_at": "2024-08-21 08:25"
    },
    {
        "writer_id": 10145,
        "writer_name": "احمد فرخی",
        "description": "پارکینگ شخصی ندارد و باید در خیابان پارک کرد.",
        "building_id": 4,
        "created_at": "2024-09-11 12:51"
    },
    {
        "writer_id": 10146,
        "writer_name": "عرفان سلیمانی",
        "description": "سرعت اینترنت در این محل خوب نیست.",
        "building_id": 4,
        "created_at": "2024-08-24 02:06"
    },
    {
        "writer_id": 10147,
        "writer_name": "رضا مرادی",
        "description": "ملک در موقعیت خوبی قرار دارد.",
        "building_id": 4,
        "created_at": "2024-09-12 10:50"
    },
    {
        "writer_id": 10148,
        "writer_name": "محمد مرادی",
        "description": "فضای داخلی طراحی مدرنی داشت.",
        "building_id": 4,
        "created_at": "2024-09-05 12:03"
    },
    {
        "writer_id": 10149,
        "writer_name": "فاطمه کریمی",
        "description": "ملک به مرکز خرید نزدیک است.",
        "building_id": 4,
        "created_at": "2024-08-20 17:49"
    },
    {
        "writer_id": 10150,
        "writer_name": "عرفان احمدی",
        "description": "فضای حیاط بزرگ و دلباز است.",
        "building_id": 4,
        "created_at": "2024-09-05 13:48"
    },
    {
        "writer_id": 10151,
        "writer_name": "فاطمه کاظمی",
        "description": "به نظر می‌رسد مالک در نگهداری ملک کوتاهی کرده.",
        "building_id": 4,
        "created_at": "2024-08-14 04:36"
    },
    {
        "writer_id": 10152,
        "writer_name": "محمد موسوی",
        "description": "محیط بسیار ساکت و آرام است.",
        "building_id": 4,
        "created_at": "2024-08-21 05:17"
    },
    {
        "writer_id": 10153,
        "writer_name": "علی فرخی",
        "description": "ملک از عکس‌ها بهتر بود.",
        "building_id": 4,
        "created_at": "2024-09-10 11:56"
    },
    {
        "writer_id": 10154,
        "writer_name": "فاطمه نعمتی",
        "description": "محیط بسیار ساکت و آرام است.",
        "building_id": 4,
        "created_at": "2024-08-15 11:05"
    },
    {
        "writer_id": 10155,
        "writer_name": "محمد موسوی",
        "description": "فضای نشیمن بزرگ و جادار بود.",
        "building_id": 4,
        "created_at": "2024-08-29 00:43"
    },
    {
        "writer_id": 10156,
        "writer_name": "حسین مرادی",
        "description": "دسترسی به مراکز خرید خیلی خوب بود.",
        "building_id": 4,
        "created_at": "2024-08-28 23:00"
    },
    {
        "writer_id": 10157,
        "writer_name": "فاطمه رضایی",
        "description": "محیط بسیار ساکت و آرام است.",
        "building_id": 4,
        "created_at": "2024-08-20 07:30"
    },
    {
        "writer_id": 10158,
        "writer_name": "علی فرخی",
        "description": "نزدیکی به بیمارستان از نکات مثبت است.",
        "building_id": 4,
        "created_at": "2024-09-13 18:21"
    },
    {
        "writer_id": 10159,
        "writer_name": "احمد سلیمانی",
        "description": "ملک در نزدیکی ایستگاه مترو قرار دارد.",
        "building_id": 4,
        "created_at": "2024-08-19 13:46"
    },
    {
        "writer_id": 10160,
        "writer_name": "احمد نعمتی",
        "description": "سرعت اینترنت در این محل خوب نیست.",
        "building_id": 4,
        "created_at": "2024-09-02 09:05"
    },
    {
        "writer_id": 10161,
        "writer_name": "زهرا سلیمانی",
        "description": "سروصدای زیاد از خیابان وجود داشت.",
        "building_id": 4,
        "created_at": "2024-08-30 21:09"
    },
    {
        "writer_id": 10162,
        "writer_name": "حسین فرخی",
        "description": "ساخت ملک نسبتاً جدید بود.",
        "building_id": 4,
        "created_at": "2024-08-26 20:11"
    },
    {
        "writer_id": 10163,
        "writer_name": "حسین احمدی",
        "description": "پارکینگ کافی نبود و باید روی خیابان پارک کنیم.",
        "building_id": 4,
        "created_at": "2024-08-28 15:43"
    },
    {
        "writer_id": 10164,
        "writer_name": "رضا کریمی",
        "description": "سیستم ایمنی خوبی دارد.",
        "building_id": 4,
        "created_at": "2024-09-10 14:48"
    },
    {
        "writer_id": 10165,
        "writer_name": "محمد کریمی",
        "description": "با وجود اینکه ملک قدیمی است، باز هم ارزش خرید دارد.",
        "building_id": 4,
        "created_at": "2024-08-18 14:15"
    },
    {
        "writer_id": 10166,
        "writer_name": "رضا فرخی",
        "description": "محله ملک جدید و مدرن است.",
        "building_id": 4,
        "created_at": "2024-08-17 21:54"
    },
    {
        "writer_id": 10167,
        "writer_name": "رضا فرخی",
        "description": "فضای اتاق‌ها نسبتاً کوچک است.",
        "building_id": 4,
        "created_at": "2024-08-17 13:29"
    },
    {
        "writer_id": 10168,
        "writer_name": "زهرا فرخی",
        "description": "محله ملک جدید و مدرن است.",
        "building_id": 4,
        "created_at": "2024-08-17 11:26"
    },
    {
        "writer_id": 10169,
        "writer_name": "مینا مرادی",
        "description": "ملک در نزدیکی ایستگاه مترو قرار دارد.",
        "building_id": 4,
        "created_at": "2024-09-05 02:18"
    },
    {
        "writer_id": 10170,
        "writer_name": "احمد فرخی",
        "description": "برای خانواده‌ها خیلی مناسب نیست.",
        "building_id": 4,
        "created_at": "2024-08-31 20:11"
    },
    {
        "writer_id": 10171,
        "writer_name": "احمد رضایی",
        "description": "نور طبیعی خوبی داشت.",
        "building_id": 4,
        "created_at": "2024-09-10 06:43"
    },
    {
        "writer_id": 10172,
        "writer_name": "عرفان رضایی",
        "description": "این ملک نیاز به بازسازی داشت.",
        "building_id": 4,
        "created_at": "2024-08-25 06:24"
    },
    {
        "writer_id": 10173,
        "writer_name": "نگار رضایی",
        "description": "پارکینگ شخصی ندارد و باید در خیابان پارک کرد.",
        "building_id": 4,
        "created_at": "2024-09-01 11:04"
    },
    {
        "writer_id": 10174,
        "writer_name": "علی فرخی",
        "description": "بسیار نزدیک به مدارس و دانشگاه‌ها است.",
        "building_id": 4,
        "created_at": "2024-08-22 21:13"
    },
    {
        "writer_id": 10175,
        "writer_name": "فاطمه محمودی",
        "description": "از خرید خود راضی هستم.",
        "building_id": 4,
        "created_at": "2024-08-17 17:53"
    },
    {
        "writer_id": 10176,
        "writer_name": "فاطمه فرخی",
        "description": "ملک در موقعیت خوبی قرار دارد.",
        "building_id": 4,
        "created_at": "2024-09-08 15:37"
    },
    {
        "writer_id": 10177,
        "writer_name": "احمد رضایی",
        "description": "دسترسی به مدرسه‌ها نزدیک است.",
        "building_id": 4,
        "created_at": "2024-08-18 06:24"
    },
    {
        "writer_id": 10178,
        "writer_name": "فاطمه نعمتی",
        "description": "نور طبیعی خوبی داشت.",
        "building_id": 4,
        "created_at": "2024-08-22 20:02"
    },
    {
        "writer_id": 10179,
        "writer_name": "عرفان مرادی",
        "description": "هزینه‌های نگهداری ملک کمی بالا است.",
        "building_id": 4,
        "created_at": "2024-09-10 00:11"
    },
    {
        "writer_id": 10180,
        "writer_name": "فاطمه فرخی",
        "description": "سرویس بهداشتی‌ها کوچک بودند.",
        "building_id": 4,
        "created_at": "2024-09-08 11:00"
    },
    {
        "writer_id": 10181,
        "writer_name": "احمد رضایی",
        "description": "ملک به مرکز خرید نزدیک است.",
        "building_id": 4,
        "created_at": "2024-08-30 10:09"
    },
    {
        "writer_id": 10182,
        "writer_name": "عرفان نعمتی",
        "description": "ساخت و ساز اطراف ملک زیاد بود.",
        "building_id": 4,
        "created_at": "2024-08-31 21:34"
    },
    {
        "writer_id": 10183,
        "writer_name": "محمد کریمی",
        "description": "از خرید خود راضی هستم.",
        "building_id": 4,
        "created_at": "2024-08-31 19:32"
    },
    {
        "writer_id": 10184,
        "writer_name": "نگار محمودی",
        "description": "آشپزخانه کوچک است، اما قابل قبول.",
        "building_id": 4,
        "created_at": "2024-09-06 06:59"
    },
    {
        "writer_id": 10185,
        "writer_name": "محمد نعمتی",
        "description": "تمیز و مرتب بود، ولی پارکینگ کوچک داشت.",
        "building_id": 4,
        "created_at": "2024-09-08 18:10"
    },
    {
        "writer_id": 10186,
        "writer_name": "علی محمودی",
        "description": "ملک دور از امکانات شهری بود.",
        "building_id": 4,
        "created_at": "2024-09-02 20:57"
    },
    {
        "writer_id": 10187,
        "writer_name": "علی فرخی",
        "description": "ملک در موقعیت خوبی قرار دارد.",
        "building_id": 4,
        "created_at": "2024-08-19 13:15"
    },
    {
        "writer_id": 10188,
        "writer_name": "زهرا نعمتی",
        "description": "خدمات محلی و دسترسی به سوپرمارکت عالی است.",
        "building_id": 4,
        "created_at": "2024-08-21 06:51"
    },
    {
        "writer_id": 10189,
        "writer_name": "رضا رضایی",
        "description": "از تهویه ملک رضایت دارم.",
        "building_id": 4,
        "created_at": "2024-09-12 22:50"
    },
    {
        "writer_id": 10190,
        "writer_name": "محمد رضایی",
        "description": "قیمت ملک نسبت به شرایط آن مناسب است.",
        "building_id": 4,
        "created_at": "2024-09-07 06:48"
    },
    {
        "writer_id": 10191,
        "writer_name": "احمد سلیمانی",
        "description": "ملک از عکس‌ها بهتر بود.",
        "building_id": 4,
        "created_at": "2024-08-16 17:20"
    },
    {
        "writer_id": 10192,
        "writer_name": "نگار فرخی",
        "description": "سروصدای زیاد از خیابان وجود داشت.",
        "building_id": 4,
        "created_at": "2024-08-25 04:35"
    },
    {
        "writer_id": 10193,
        "writer_name": "زهرا نعمتی",
        "description": "ملک بسیار تمیز و مرتب تحویل داده شد.",
        "building_id": 4,
        "created_at": "2024-09-03 08:39"
    },
    {
        "writer_id": 10194,
        "writer_name": "رضا کریمی",
        "description": "با وجود اینکه ملک قدیمی است، باز هم ارزش خرید دارد.",
        "building_id": 4,
        "created_at": "2024-08-23 13:33"
    }
]